odoo/addons/web_editor_class_selector/README.rst
odoo/addons/web_editor_class_selector/__init__.py
odoo/addons/web_editor_class_selector/__manifest__.py
odoo/addons/web_editor_class_selector/demo/web_editor_class_demo.xml
odoo/addons/web_editor_class_selector/i18n/it.po
odoo/addons/web_editor_class_selector/i18n/web_editor_class_selector.pot
odoo/addons/web_editor_class_selector/models/__init__.py
odoo/addons/web_editor_class_selector/models/web_editor_class.py
odoo/addons/web_editor_class_selector/readme/DESCRIPTION.md
odoo/addons/web_editor_class_selector/readme/ROADMAP.md
odoo/addons/web_editor_class_selector/readme/USAGE.md
odoo/addons/web_editor_class_selector/security/ir.model.access.csv
odoo/addons/web_editor_class_selector/static/description/icon.png
odoo/addons/web_editor_class_selector/static/description/index.html
odoo/addons/web_editor_class_selector/static/src/js/css_selector/css_selector.esm.js
odoo/addons/web_editor_class_selector/static/src/js/css_selector/css_selector.xml
odoo/addons/web_editor_class_selector/static/src/js/css_selector/css_selector_plugin.esm.js
odoo/addons/web_editor_class_selector/static/src/js/fields/html_field.esm.js
odoo/addons/web_editor_class_selector/static/src/js/utils/utils.esm.js
odoo/addons/web_editor_class_selector/static/src/js/wysiwyg/wysiwyg.esm.js
odoo/addons/web_editor_class_selector/static/src/scss/demo_styles.scss
odoo/addons/web_editor_class_selector/views/menus.xml
odoo/addons/web_editor_class_selector/views/web_editor_class_views.xml
odoo_addon_web_editor_class_selector-18.0.1.0.0.2.dist-info/METADATA
odoo_addon_web_editor_class_selector-18.0.1.0.0.2.dist-info/WHEEL
odoo_addon_web_editor_class_selector-18.0.1.0.0.2.dist-info/top_level.txt
odoo_addon_web_editor_class_selector-18.0.1.0.0.2.dist-info/RECORD
